CHANGELOG.rst
LICENSE.txt
MANIFEST.in
README.rst
TODO.rst
VERSION.txt
setup.cfg
setup.py
test_requirements.txt
pyramid_input/__init__.py
pyramid_input/i18n.py
pyramid_input/test.py
pyramid_input.egg-info/PKG-INFO
pyramid_input.egg-info/SOURCES.txt
pyramid_input.egg-info/dependency_links.txt
pyramid_input.egg-info/requires.txt
pyramid_input.egg-info/top_level.txt
pyramid_input.egg-info/zip-safe