Metadata-Version: 1.1
Name: pyramid-input
Version: 0.2.3
Summary: A Pyramid tween that normalizes HTTP request input data.
Home-page: http://github.com/canaryhealth/pyramid_input
Author: Philip J Grabner, Canary Health Inc
Author-email: oss-pypi@canary.md
License: MIT (http://opensource.org/licenses/MIT)
Keywords: web wsgi pyramid http input data normalize get post json yaml xml
Platform: UNKNOWN
Classifier: Intended Audience :: Developers
Classifier: Programming Language :: Python
Classifier: Framework :: Pyramid
Classifier: Environment :: Console
Classifier: Environment :: Web Environment
Classifier: Operating System :: OS Independent
Classifier: Topic :: Internet
Classifier: Topic :: Software Development
Classifier: Topic :: Internet :: WWW/HTTP
Classifier: Topic :: Internet :: WWW/HTTP :: WSGI
Classifier: Topic :: Software Development :: Libraries :: Application Frameworks
Classifier: Natural Language :: English
Classifier: License :: OSI Approved :: MIT License
Classifier: License :: Public Domain
